Contact_info/__init__.py
Contact_info/address.py
Contact_info/name.py
contact_info_package-2.0.1.dist-info/METADATA
contact_info_package-2.0.1.dist-info/WHEEL
contact_info_package-2.0.1.dist-info/top_level.txt
contact_info_package-2.0.1.dist-info/RECORD
